{
    "name": "East Tilbury",
    "position": [
        1568,
        14272
    ],
    "exits": {
        "eastbound": {
            "direction": 2,
            "requirements": {
                "unlocked": [],
                "not": []
            },
            "line": "Grays"
        },
        "westbound": {
            "direction": 10,
            "requirements": {
                "unlocked": [],
                "not": []
            },
            "line": "Grays"
        }
    },
    "map_text": [
        {
            "offset": [
                -16,
                -8
            ],
            "text": "East Tilbury",
            "font": "Arial 10",
            "anchor": "se"
        }
    ],
    "passengers": {
        "chance_of_any": 60,
        "options": []
    },
    "shop": false
}