{
    "name": "Limehouse",
    "position": [
        -3272,
        14656
    ],
    "exits": {
        "eastbound": {
            "direction": 3,
            "requirements": {
                "unlocked": [],
                "not": []
            },
            "line": "Fenchurch St"
        },
        "westbound": {
            "direction": 11,
            "requirements": {
                "unlocked": [],
                "not": []
            },
            "line": "Fenchurch St"
        }
    },
    "map_text": [
        {
            "offset": [
                -16,
                -16
            ],
            "text": "Limehouse",
            "font": "Arial 10",
            "anchor": "se"
        }
    ],
    "passengers": {
        "chance_of_any": 60,
        "options": [
            {
                "chance": 2,
                "station": "EastAnglia/Barking",
                "line": [
                    "EastAnglia/Barking-E",
                    "EastAnglia/Barking"
                ],
                "reward": 1
            },
            {
                "chance": 2,
                "station": "EastAnglia/West Ham",
                "line": [
                    "EastAnglia/Fenchurch St"
                ],
                "reward": 1
            },
            {
                "chance": 3,
                "station": "EastAnglia/Fenchurch Street",
                "line": [
                    "EastAnglia/Fenchurch St"
                ],
                "reward": 1
            }
        ]
    },
    "shop": false
}