{
    "colour": "#FFCD00",
    "requirements": {
        "unlocked": [
            "LondonUnderground/H+C",
            "LondonUnderground/Circle-J2"
        ],
        "not": []
    },
    "segments": [
        [
            -2184,
            -128,
            -2204,
            -118
        ],
        [
            -2200,
            -120,
            -2908,
            -120
        ],
        [
            -2908,
            -120,
            -2956,
            -96
        ],
        [
            -3496,
            444,
            -2956,
            -96
        ],
        [
            -3496,
            444,
            -3520,
            492
        ],
        [
            -3520,
            492,
            -3520,
            1204
        ]
    ],
    "corners": [
        [
            -2184,
            -128,
            4,
            11
        ],
        [
            -2200,
            -120,
            3,
            12
        ],
        [
            -2908,
            -120,
            4,
            11
        ],
        [
            -3496,
            444,
            2,
            9
        ],
        [
            -3520,
            492,
            1,
            8
        ]
    ]
}